nanome/__init__.py
nanome/plugin-template.zip
nanome/plugin_init.py
nanome/setup_config.py
nanome/_internal/__init__.py
nanome/_internal/addon.py
nanome/_internal/decorators.py
nanome/_internal/enum_utils.py
nanome/_internal/enums.py
nanome/_internal/logs.py
nanome/_internal/plugin_instance_async.py
nanome/_internal/py2_enum.py
nanome/_internal/serializer_fields.py
nanome/_internal/network/__init__.py
nanome/_internal/network/context.py
nanome/_internal/network/data.py
nanome/_internal/network/net_instance.py
nanome/_internal/network/packet.py
nanome/_internal/network/plugin_network.py
nanome/_internal/network/session.py
nanome/_internal/process/__init__.py
nanome/_internal/process/bonding.py
nanome/_internal/process/dssp.py
nanome/_internal/process/process_entry.py
nanome/_internal/process/process_manager.py
nanome/_internal/process/process_manager_instance.py
nanome/_internal/process/external/dssp/dssp-3.0.0-win32.exe
nanome/_internal/process/external/dssp/dssp-linux
nanome/_internal/structure/__init__.py
nanome/_internal/structure/models.py
nanome/_internal/structure/helpers/__init__.py
nanome/_internal/structure/helpers/conformer_helper.py
nanome/_internal/structure/helpers/copy.py
nanome/_internal/structure/io/__init__.py
nanome/_internal/structure/io/mmcif/__init__.py
nanome/_internal/structure/io/mmcif/content.py
nanome/_internal/structure/io/mmcif/parse.py
nanome/_internal/structure/io/mmcif/save.py
nanome/_internal/structure/io/mmcif/structure.py
nanome/_internal/structure/io/pdb/__init__.py
nanome/_internal/structure/io/pdb/content.py
nanome/_internal/structure/io/pdb/parse.py
nanome/_internal/structure/io/pdb/save.py
nanome/_internal/structure/io/pdb/structure.py
nanome/_internal/structure/io/sdf/__init__.py
nanome/_internal/structure/io/sdf/content.py
nanome/_internal/structure/io/sdf/parse.py
nanome/_internal/structure/io/sdf/save.py
nanome/_internal/structure/io/sdf/structure.py
nanome/_internal/ui/__init__.py
nanome/_internal/ui/models.py
nanome-0.42.1.dist-info/LICENSE
nanome-0.42.1.dist-info/METADATA
nanome-0.42.1.dist-info/WHEEL
nanome-0.42.1.dist-info/entry_points.txt
nanome-0.42.1.dist-info/top_level.txt
nanome-0.42.1.dist-info/RECORD
