Metadata-Version: 2.2
Name: nanome
Version: 0.42.1
Summary: Python API for Nanome Plugins
Home-page: https://github.com/nanome-ai/nanome
Author: Nanome
Author-email: hello@nanome.ai
License: MIT
Keywords: virtual-reality,chemistry,python,api,plugin
Platform: any
Classifier: Development Status :: 3 - Alpha
Classifier: Intended Audience :: Science/Research
Classifier: Topic :: Scientific/Engineering :: Chemistry
Classifier: License :: OSI Approved :: MIT License
Classifier: Programming Language :: Python :: 2.7
Classifier: Programming Language :: Python :: 3.5
Classifier: Programming Language :: Python :: 3.6
Classifier: Programming Language :: Python :: 3.7
License-File: LICENSE
Requires-Dist: tblib>=1.7.0
Requires-Dist: graypy>=2.1.0
Provides-Extra: schemas
Requires-Dist: marshmallow>=3.18.0; extra == "schemas"
Provides-Extra: beta
Requires-Dist: redis>=4.1.3; extra == "beta"
Dynamic: author
Dynamic: author-email
Dynamic: classifier
Dynamic: description
Dynamic: description-content-type
Dynamic: home-page
Dynamic: keywords
Dynamic: license
Dynamic: platform
Dynamic: provides-extra
Dynamic: requires-dist
Dynamic: summary
